{
  "heatmapData": [
    { "cohort": "Jan 2025", "week1": 100, "week2": 89, "week3": 74, "week4": 65, "week5": 56, "week6": 52, "week7": 43, "week8": 41, "week9": 34, "week10": 30, "week11": 25, "week12": 24 },
    { "cohort": "Feb 2025", "week1": 100, "week2": 89, "week3": 74, "week4": 68, "week5": 58, "week6": 53, "week7": 45, "week8": 40, "week9": 33, "week10": 33, "week11": 25, "week12": 26 },
    { "cohort": "Mar 2025", "week1": 100, "week2": 88, "week3": 75, "week4": 69, "week5": 59, "week6": 53, "week7": 42, "week8": 38, "week9": 36, "week10": 30, "week11": 26, "week12": 22 },
    { "cohort": "Apr 2025", "week1": 100, "week2": 87, "week3": 76, "week4": 68, "week5": 56, "week6": 51, "week7": 44, "week8": 39, "week9": 33, "week10": 30, "week11": 25, "week12": 21 },
    { "cohort": "May 2025", "week1": 100, "week2": 87, "week3": 75, "week4": 66, "week5": 56, "week6": 50, "week7": 44, "week8": 41, "week9": 33, "week10": 32, "week11": 22, "week12": 22 },
    { "cohort": "Jun 2025", "week1": 100, "week2": 86, "week3": 75, "week4": 66, "week5": 59, "week6": 49, "week7": 43, "week8": 38, "week9": 33, "week10": 28, "week11": 23, "week12": 23 },
    { "cohort": "Jul 2025", "week1": 100, "week2": 86, "week3": 76, "week4": 67, "week5": 57, "week6": 51, "week7": 43, "week8": 37, "week9": 36, "week10": 30, "week11": 26, "week12": 22 },
    { "cohort": "Aug 2025", "week1": 100, "week2": 88, "week3": 78, "week4": 70, "week5": 60, "week6": 51, "week7": 44, "week8": 39, "week9": 34, "week10": 33, "week11": 24, "week12": 23 },
    { "cohort": "Sep 2025", "week1": 100, "week2": 88, "week3": 78, "week4": 66, "week5": 59, "week6": 51, "week7": 47, "week8": 40, "week9": 37, "week10": 32, "week11": 25, "week12": 23 },
    { "cohort": "Oct 2025", "week1": 100, "week2": 86, "week3": 76, "week4": 68, "week5": 56, "week6": 52, "week7": 45, "week8": 40, "week9": 36, "week10": 28, "week11": 19, "week12": 11 },
    { "cohort": "Nov 2025", "week1": 100, "week2": 86, "week3": 77, "week4": 70, "week5": 59, "week6": 53, "week7": 34, "week8": 21, "week9": 7, "week10": null, "week11": null, "week12": null }
  ],
  "cohortComparison": [
    {
      "week": 1,
      "Q1_2025": 100,
      "Q2_2025": 100,
      "Q3_2025": 100,
      "Q4_2025": 100
    },
    {
      "week": 2,
      "Q1_2025": 89,
      "Q2_2025": 87,
      "Q3_2025": 87,
      "Q4_2025": 86
    },
    {
      "week": 3,
      "Q1_2025": 74,
      "Q2_2025": 75,
      "Q3_2025": 77,
      "Q4_2025": 76
    },
    {
      "week": 4,
      "Q1_2025": 67,
      "Q2_2025": 67,
      "Q3_2025": 68,
      "Q4_2025": 69
    },
    {
      "week": 5,
      "Q1_2025": 58,
      "Q2_2025": 57,
      "Q3_2025": 59,
      "Q4_2025": 58
    },
    {
      "week": 6,
      "Q1_2025": 53,
      "Q2_2025": 50,
      "Q3_2025": 51,
      "Q4_2025": 52
    },
    {
      "week": 7,
      "Q1_2025": 43,
      "Q2_2025": 44,
      "Q3_2025": 45,
      "Q4_2025": 40
    },
    {
      "week": 8,
      "Q1_2025": 40,
      "Q2_2025": 39,
      "Q3_2025": 39,
      "Q4_2025": 30
    },
    {
      "week": 9,
      "Q1_2025": 34,
      "Q2_2025": 33,
      "Q3_2025": 36,
      "Q4_2025": 22
    },
    {
      "week": 10,
      "Q1_2025": 31,
      "Q2_2025": 30,
      "Q3_2025": 32,
      "Q4_2025": 28
    },
    {
      "week": 11,
      "Q1_2025": 25,
      "Q2_2025": 23,
      "Q3_2025": 25,
      "Q4_2025": 19
    },
    {
      "week": 12,
      "Q1_2025": 24,
      "Q2_2025": 22,
      "Q3_2025": 23,
      "Q4_2025": 11
    }
  ]
}





